LICENSE
package.json
examples/pyside/README.md
examples/pyside/requirements.txt
examples/pyside/run.py
examples/testbed/README.md
examples/testbed/requirements.txt
examples/testbed/run.py
examples/webruntime/README.md
examples/webruntime/requirements.txt
examples/webruntime/run.py
examples/webruntime/run.spec
sidegears/__init__.py
sidegears/version.py
sidegears/kernel/__init__.py
sidegears/kernel/kernel.py
sidegears-0.1.6.dist-info/LICENSE
sidegears-0.1.6.dist-info/METADATA
sidegears-0.1.6.dist-info/WHEEL
sidegears-0.1.6.dist-info/top_level.txt
sidegears-0.1.6.dist-info/RECORD
