Metadata-Version: 2.1
Name: sidegears
Version: 0.1.6
Summary: Tools for browser-based desktop applications
Home-page: https://gitlab.com/john.tourtellott/sidegears
Author: john Tourtellott
Author-email: john.turtle@gmail.com
License: UNKNOWN
Platform: UNKNOWN
Classifier: Programming Language :: Python :: 3
Classifier: License :: OSI Approved :: ISC License (ISCL)
Classifier: Operating System :: OS Independent
Requires-Dist: jsonrpcserver
Requires-Dist: websockets
